imlazy/__init__.py
imlazy/commander.py
imlazy/docker.py
imlazy-1.3.1.1.data/scripts/dcu
imlazy-1.3.1.1.data/scripts/dockerlist
imlazy-1.3.1.1.data/scripts/dockerrm
imlazy-1.3.1.1.data/scripts/dockerssh
imlazy-1.3.1.1.data/scripts/dockerstop
imlazy-1.3.1.1.data/scripts/pipit
imlazy-1.3.1.1.dist-info/LICENSE
imlazy-1.3.1.1.dist-info/METADATA
imlazy-1.3.1.1.dist-info/WHEEL
imlazy-1.3.1.1.dist-info/top_level.txt
imlazy-1.3.1.1.dist-info/RECORD
