Metadata-Version: 2.1
Name: imlazy
Version: 1.3.1.1
Summary: UNKNOWN
Home-page: https://github.com/smeggingsmegger/imlazy
License: UNKNOWN
Keywords: helpful misc utilities
Platform: UNKNOWN
Requires-Dist: setuptools
